tests/__init__.py
tests/test_area.py
tests/test_density.py
tests/test_flow_rate.py
tests/test_humidity.py
tests/test_length.py
tests/test_mass.py
tests/test_pressure.py
tests/test_tds.py
tests/test_temps.py
tests/test_time.py
tests/test_volume.py
units_converter/__init__.py
units_converter/area.py
units_converter/base.py
units_converter/conc.py
units_converter/density.py
units_converter/flow_rate.py
units_converter/humidity.py
units_converter/length.py
units_converter/mass.py
units_converter/pressure.py
units_converter/tds.py
units_converter/temp.py
units_converter/time.py
units_converter/volume.py
cwt_units_converter-0.1.9.dist-info/METADATA
cwt_units_converter-0.1.9.dist-info/WHEEL
cwt_units_converter-0.1.9.dist-info/top_level.txt
cwt_units_converter-0.1.9.dist-info/RECORD
